<?xml version="1.0" encoding="utf-8"?>
<odoo>
    <data>
        <record model="ir.ui.view" id="product_product_inherit_form">
            <field name="name">product.product.inherit.form</field>
            <field name="model">product.product</field>
            <field name="inherit_id" ref="product.product_normal_form_view"/>
            <field name="arch" type="xml">
                <div name="button_box" position="inside">
                    <button class="oe_stat_button" type="object" name="action_view_vendor" icon="fa-industry">
                        <field string="Vendor" name="total_vendor" widget="statinfo"/>
                    </button>
                </div>
            </field>
        </record>

    </data>
</odoo>