<?xml version="1.0" encoding="utf-8"?>
<odoo>
    <data>
        <record id="makloon_order_product_inherit1" model="ir.ui.view">
             <field name="name">makloon.order.product.template.inherit1</field>
             <field name="model">product.template</field>
             <field name="inherit_id" ref="product.product_template_only_form_view"/>
             <field name="arch" type="xml">
                <field name="categ_id" position="after">
                     <field name="product_group_category"/>
                </field>
             </field>
        </record>
        <record id="makloon_order_product_inherit_tree1" model="ir.ui.view">
             <field name="name">makloon.order.product.template.inherit.tree1</field>
             <field name="model">product.template</field>
             <field name="inherit_id" ref="product.product_template_tree_view"/>
             <field name="arch" type="xml">
                <field name="categ_id" position="after">
                     <field name="product_group_category"/>
                </field>
             </field>
        </record>
    </data>
</odoo>