<odoo>
    <data>

        <report id="action_sale_contract" model="sale.contract" string="sale contract" report_type="qweb-pdf"
            name="sale_contract.sale_contract" file="sale_contract.sale_contract" />

        <template id="sale_contract">
            <t t-foreach="docs" t-as="o">
                <div class="page">
                    <div>
                        <img src="/web/binary/company_logo" style="width:20%; padding:20px 0px" align="left" />
                    </div>
                    <br />
                    <div class="row">
                        <div style="font-size:30px" class="col-xs-9">
                            <table class="table table-condensed">
                                <tr>
                                    <td style="border: 1px solid white" />
                                </tr>
                                <tr>
                                    <td class="text-center"><strong>SALES CONTRACT</strong></td>
                                </tr>
                                <tr class="border-black">
                                    <td class="text-center"><strong>No. Sales Contract : </strong></td>
                                </tr>
                            </table>
                        </div>
                    </div>
                    <div class="row">
                        <div style="font-size:17px;margin-top:-30px" class="col-xs-6">
                            <table class="table table-condensed">
                                <tr>
                                    <td style="border: 1px solid white" class="text-left"><strong>Tanggal</strong></td>
                                    <td style="border: 1px solid white" class="text-left"><strong>:</strong></td>
                                    <td style="border: 1px solid white" class="text-left"><span
                                            t-field="o.date_order" /></td>
                                </tr>
                                <tr>
                                    <td style="border: 1px solid white" class="text-left"><strong>Cust Code</strong>
                                    </td>
                                    <td style="border: 1px solid white" class="text-left"><strong>:</strong></td>
                                    <td style="border: 1px solid white" class="text-left"><span
                                            t-field="o.partner_id.ref" /></td>
                                </tr>
                                <tr>
                                    <td style="border: 1px solid white" class="text-left"><strong>Jenis
                                            Transaksi</strong></td>
                                    <td style="border: 1px solid white" class="text-left"><strong>:</strong></td>
                                    <td style="border: 1px solid white" class="text-left">
                                        <!--<span t-field="o.sales_type"/>-->
                                    </td>
                                </tr>
                                <tr>
                                    <td style="border: 1px solid white" class="text-left"><strong>Kode Hanger</strong>
                                    </td>
                                    <td style="border: 1px solid white" class="text-left"><strong>:</strong></td>
                                    <td style="border: 1px solid white" class="text-left">
                                        <!--<span t-field="o.td_id"/>-->
                                    </td>
                                </tr>
                                <tr>
                                    <td style="border: 1px solid white" class="text-left"><strong>Nama Greige</strong>
                                    </td>
                                    <td style="border: 1px solid white" class="text-left"><strong>:</strong></td>
                                    <td style="border: 1px solid white" class="text-left">
                                        <!--<span t-field="o.greige_name"/>-->
                                    </td>
                                </tr>
                                <tr>
                                    <td style="border: 1px solid white" class="text-left"><strong>Qty</strong></td>
                                    <td style="border: 1px solid white" class="text-left"><strong>:</strong></td>
                                    <td style="border: 1px solid white" class="text-left"><span t-field="o.qty_order" />
                                    </td>
                                </tr>
                                <tr>
                                    <td style="border: 1px solid white" class="text-center"><strong>Pirce</strong></td>
                                </tr>
                                <tr>
                                    <td style="border: 1px solid white" class="text-left"><strong>BW</strong></td>
                                    <td style="border: 1px solid white" class="text-left"><strong>:</strong></td>
                                    <td style="border: 1px solid white" class="text-left">
                                        <!--<span t-field="o.date_order"/>-->
                                    </td>
                                </tr>
                                <tr>
                                    <td style="border: 1px solid white" class="text-left"><strong>Light</strong></td>
                                    <td style="border: 1px solid white" class="text-left"><strong>:</strong></td>
                                    <td style="border: 1px solid white" class="text-left">
                                        <!--<span t-field="o.date_order"/>-->
                                    </td>
                                </tr>
                                <tr>
                                    <td style="border: 1px solid white" class="text-left"><strong>Medium</strong></td>
                                    <td style="border: 1px solid white" class="text-left"><strong>:</strong></td>
                                    <td style="border: 1px solid white" class="text-left">
                                        <!--<span t-field="o.date_order"/>-->
                                    </td>
                                </tr>
                            </table>
                        </div>
                    </div>
                    <div class="row">
                        <div style="font-size:17px;margin-top:-370px" class="col-xs-6 col-xs-offset-6">
                            <table class="table table-condensed">
                                <tr>
                                    <td style="border: 1px solid white" class="text-left"><strong>Proses</strong></td>
                                    <td style="border: 1px solid white" class="text-left"><strong>:</strong></td>
                                    <td style="border: 1px solid white" class="text-left">
                                        <!--<span t-field="o.process"/>-->
                                    </td>
                                </tr>
                                <tr>
                                    <td style="border: 1px solid white" class="text-left"><strong>Min Qty Order Per
                                            Warna</strong></td>
                                    <td style="border: 1px solid white" class="text-left"><strong>:</strong></td>
                                    <td style="border: 1px solid white" class="text-left"><span
                                            t-field="o.min_qty_color" /></td>
                                </tr>
                                <tr>
                                    <td style="border: 1px solid white" class="text-left"><strong>Toleransi Grd
                                            B</strong></td>
                                    <td style="border: 1px solid white" class="text-left"><strong>:</strong></td>
                                    <td style="border: 1px solid white" class="text-left">
                                        <!--<span t-field="o.persen_grade_b"/>-->
                                    </td>
                                </tr>
                                <tr>
                                    <td style="border: 1px solid white" class="text-left"><strong>Toleransi
                                            Susut</strong></td>
                                    <td style="border: 1px solid white" class="text-left"><strong>:</strong></td>
                                    <td style="border: 1px solid white" class="text-left">
                                        <!--<span t-field="o.date_order"/>-->
                                    </td>
                                </tr>
                                <tr>
                                    <td style="border: 1px solid white" class="text-left"><strong>TOP</strong></td>
                                    <td style="border: 1px solid white" class="text-left"><strong>:</strong></td>
                                    <td style="border: 1px solid white" class="text-left"><span
                                            t-field="o.term_of_payment" /></td>
                                </tr>
                                <tr>
                                    <td style="border: 1px solid white" class="text-left"><strong>Periode</strong></td>
                                    <td style="border: 1px solid white" class="text-left"><strong>:</strong></td>
                                    <td style="border: 1px solid white" class="text-left">
                                        <!--<span t-field="o.date_order"/>-->
                                    </td>
                                </tr>
                                <tr>
                                    <td style="border: 1px solid white">
                                        <br />
                                    </td>
                                </tr>
                                <tr>
                                    <td style="border: 1px solid white" class="text-left"><strong>Dark</strong></td>
                                    <td style="border: 1px solid white" class="text-left"><strong>:</strong></td>
                                    <td style="border: 1px solid white" class="text-left">
                                        <!--<span t-field="o.date_order"/>-->
                                    </td>
                                </tr>
                                <tr>
                                    <td style="border: 1px solid white" class="text-left"><strong>Spesial</strong></td>
                                    <td style="border: 1px solid white" class="text-left"><strong>:</strong></td>
                                    <td style="border: 1px solid white" class="text-left">
                                        <!--<span t-field="o.date_order"/>-->
                                    </td>
                                </tr>
                            </table>
                        </div>
                    </div>
                    <table class="table" style="margin-top:-10px">
                        <tr>
                            <td class="text-center" style="border: 1px solid white"><strong>Marketing</strong></td>
                            <td class="text-center" style="border: 1px solid white"><strong>Customer</strong></td>
                        </tr>
                        <tr style="padding-top:200px">
                            <td class="text-center" style="border: 1px solid white"><br /><br /><br /><strong>
                                    ___________________</strong></td>
                            <td class="text-center" style="border: 1px solid white"><br /><br /><br /><strong>
                                    ___________________</strong></td>
                        </tr>
                    </table>
                    <div style="margin-top:-30px">
                        <h4>
                            <b>Note : Ditagihkan berdasarkan _________________________</b>
                        </h4>
                    </div>


                    <div class="row">
                        <div style="font-size:30px;margin-top:-5px" class="col-xs-9 col-xs-offset-2">
                            <table class="table table-condensed">
                                <tr>
                                    <td style="border: 1px solid white" />
                                </tr>
                                <tr>
                                    <td class="text-center"><strong>SALES CONTRACT</strong></td>
                                </tr>
                            </table>
                        </div>
                    </div>

                    <div class="row">
                        <div style="font-size:17px;margin-top:-30px" class="col-xs-6 col-xs-offset-6">
                            <table class="table table-condensed">
                                <tr>
                                    <td style="border: 1px solid white" class="text-left"><strong>No. Sales
                                            Contract</strong></td>
                                    <td style="border: 1px solid white" class="text-left"><strong>:</strong></td>
                                    <td style="border: 1px solid white" class="text-left"><span t-field="o.name" /></td>
                                </tr>
                                <tr>
                                    <td style="border: 1px solid white" class="text-left"><strong>Kode Hanger</strong>
                                    </td>
                                    <td style="border: 1px solid white" class="text-left"><strong>:</strong></td>
                                    <td style="border: 1px solid white" class="text-left">
                                        <!--<span t-field="o.td_id"/>-->
                                    </td>
                                </tr>
                                <tr>
                                    <td style="border: 1px solid white" class="text-left"><strong>Proses</strong></td>
                                    <td style="border: 1px solid white" class="text-left"><strong>:</strong></td>
                                    <td style="border: 1px solid white" class="text-left">
                                        <!--<span t-field="o.process"/>-->
                                    </td>
                                </tr>
                            </table>
                        </div>
                    </div>
                    <div class="row">
                        <div style="font-size:17px;margin-top:-125px" class="col-xs-9">
                            <table class="table table-condensed">
                                <tr>
                                    <td style="border: 1px solid white" class="text-left"><strong>Tanggal</strong></td>
                                    <td style="border: 1px solid white" class="text-left"><strong>:</strong></td>
                                    <td style="border: 1px solid white" class="text-left"><span
                                            t-field="o.date_order" /></td>
                                </tr>
                                <tr>
                                    <td style="border: 1px solid white" class="text-left"><strong>Cust Code</strong>
                                    </td>
                                    <td style="border: 1px solid white" class="text-left"><strong>:</strong></td>
                                    <td style="border: 1px solid white" class="text-left"><span
                                            t-field="o.partner_id.ref" /></td>
                                </tr>
                                <tr>
                                    <td style="border: 1px solid white" class="text-left"><strong>Jenis
                                            Transaksi</strong></td>
                                    <td style="border: 1px solid white" class="text-left"><strong>:</strong></td>
                                    <td style="border: 1px solid white" class="text-left">
                                        <!--<span t-field="o.sales_type"/>-->
                                    </td>
                                </tr>
                                <tr>
                                    <td style="border: 1px solid white" class="text-left"><strong>Nama Greige</strong>
                                    </td>
                                    <td style="border: 1px solid white" class="text-left"><strong>:</strong></td>
                                    <td style="border: 1px solid white" class="text-left">
                                        <!--<span t-field="o.greige_name"/>-->
                                    </td>
                                </tr>
                                <tr>
                                    <td style="border: 1px solid white" class="text-left">
                                        <strong><i>Spesifikasi</i></strong></td>
                                    <td style="border: 1px solid white" class="text-left"><strong>:</strong></td>
                                    <td style="border: 1px solid white" class="text-left"><strong>Lebar Greige</strong>
                                    </td>
                                    <td style="border: 1px solid white" class="text-left"><strong>:</strong></td>
                                    <td style="border: 1px solid white" class="text-left">
                                        <!-- <span t-field="o.date_order" /> -->
                                    </td>
                                </tr>
                                <tr>
                                    <td style="border: 1px solid white" class="text-left"><strong /></td>
                                    <td style="border: 1px solid white" class="text-left"><strong /></td>
                                    <td style="border: 1px solid white" class="text-left"><strong>Gramasi
                                            Greige</strong></td>
                                    <td style="border: 1px solid white" class="text-left"><strong>:</strong></td>
                                    <td style="border: 1px solid white" class="text-left">
                                        <!-- <span t-field="o.date_order" /> -->
                                    </td>
                                </tr>
                                <tr>
                                    <td style="border: 1px solid white" class="text-left"><strong /></td>
                                    <td style="border: 1px solid white" class="text-left"><strong /></td>
                                    <td style="border: 1px solid white" class="text-left"><strong>Lebar Finish</strong>
                                    </td>
                                    <td style="border: 1px solid white" class="text-left"><strong>:</strong></td>
                                    <td style="border: 1px solid white" class="text-left">
                                        <!-- <span t-field="o.date_order" /> -->
                                    </td>
                                </tr>
                                <tr>
                                    <td style="border: 1px solid white" class="text-left"><strong /></td>
                                    <td style="border: 1px solid white" class="text-left"><strong /></td>
                                    <td style="border: 1px solid white" class="text-left">
                                        <strong>Gramasi Finish</strong>
                                    </td>
                                    <td style="border: 1px solid white" class="text-left"><strong>:</strong></td>
                                    <td style="border: 1px solid white" class="text-left">
                                        <!-- <span t-field="o.date_order" /> -->
                                    </td>
                                </tr>
                                <tr>
                                    <td style="border: 1px solid white" class="text-left"><strong /></td>
                                    <td style="border: 1px solid white" class="text-left"><strong /></td>
                                    <td style="border: 1px solid white" class="text-left"><strong>Potong
                                            Pinggir</strong></td>
                                    <td style="border: 1px solid white" class="text-left"><strong>:</strong></td>
                                    <td style="border: 1px solid white" class="text-left">
                                        <!-- <span t-field="o.cutting_side" /> -->
                                    </td>
                                </tr>
                                <tr>
                                    <td style="border: 1px solid white" class="text-left">
                                        <strong><i>Inspecting</i></strong></td>
                                    <td style="border: 1px solid white" class="text-left"><strong>:</strong></td>
                                    <td style="border: 1px solid white" class="text-left"><strong>Grading</strong></td>
                                    <td style="border: 1px solid white" class="text-left"><strong>:</strong></td>
                                    <td style="border: 1px solid white" class="text-left">
                                        <!--<span t-field="o.grading"/>-->
                                    </td>
                                </tr>
                                <tr>
                                    <td style="border: 1px solid white" class="text-left"><strong /></td>
                                    <td style="border: 1px solid white" class="text-left"><strong /></td>
                                    <td style="border: 1px solid white" class="text-left"><strong>Max Joint
                                            Piece</strong></td>
                                    <td style="border: 1px solid white" class="text-left"><strong>:</strong></td>
                                    <td style="border: 1px solid white" class="text-left">
                                        <!--<span t-field="o.max_joint_pieces"/>-->
                                    </td>
                                </tr>
                                <tr>
                                    <td style="border: 1px solid white" class="text-left"><strong /></td>
                                    <td style="border: 1px solid white" class="text-left"><strong /></td>
                                    <td style="border: 1px solid white" class="text-left"><strong>Piece
                                            Length/Weight</strong></td>
                                    <td style="border: 1px solid white" class="text-left"><strong>:</strong></td>
                                    <td style="border: 1px solid white" class="text-left">
                                        <!--<span t-field="o.piece_length"/>-->
                                    </td>
                                </tr>
                                <tr>
                                    <td style="border: 1px solid white" class="text-left"><strong /></td>
                                    <td style="border: 1px solid white" class="text-left"><strong /></td>
                                    <td style="border: 1px solid white" class="text-left"><strong>Packing</strong></td>
                                    <td style="border: 1px solid white" class="text-left"><strong>:</strong></td>
                                    <td style="border: 1px solid white" class="text-left">
                                        <!--<span t-field="o.packing"/>-->
                                    </td>
                                </tr>
                                <tr>
                                    <td style="border: 1px solid white" class="text-left"><strong /></td>
                                    <td style="border: 1px solid white" class="text-left"><strong /></td>
                                    <td style="border: 1px solid white" class="text-left"><strong>Acessories</strong>
                                    </td>
                                    <td style="border: 1px solid white" class="text-left"><strong>:</strong></td>
                                    <td style="border: 1px solid white" class="text-left">
                                        <!--<span t-field="o.accessories_id"/>-->
                                    </td>
                                </tr>
                                <tr>
                                    <td style="border: 1px solid white" class="text-left"><strong /></td>
                                    <td style="border: 1px solid white" class="text-left"><strong /></td>
                                    <td style="border: 1px solid white" class="text-left"><strong>Hang Tag</strong></td>
                                    <td style="border: 1px solid white" class="text-left"><strong>:</strong></td>
                                    <td style="border: 1px solid white" class="text-left">
                                        <!--<span t-field="o.hang_tag_id"/>-->
                                    </td>
                                </tr>
                                <tr>
                                    <td style="border: 1px solid white" class="text-right"><strong>Note</strong></td>
                                    <td style="border: 1px solid white" class="text-left"><strong>:</strong></td>
                                    <td style="border: 1px solid white" class="text-left">
                                        <strong><span t-field="o.note" /></strong></td>
                                </tr>
                            </table>
                        </div>
                    </div>


                    <table class="table" style="margin-top:-30px">
                        <tr>
                            <td class="text-center" style="border: 1px solid white"><strong>Marketing</strong></td>
                            <td class="text-center" style="border: 1px solid white"><strong>Customer</strong></td>
                        </tr>
                        <tr style="padding-top:200px">
                            <td class="text-center" style="border: 1px solid white"><br /><br /><br /><strong>
                                    ___________________</strong></td>
                            <td class="text-center" style="border: 1px solid white"><br /><br /><br /><strong>
                                    ___________________</strong></td>
                        </tr>
                    </table>


                </div>
            </t>


        </template>



    </data>
</odoo>